readerCoerente/__init__.py
readerCoerente/main.py
readercoerente-0.7.1.dist-info/METADATA
readercoerente-0.7.1.dist-info/WHEEL
readercoerente-0.7.1.dist-info/RECORD
