Metadata-Version: 2.3
Name: readerCoerente
Version: 0.7.1
Summary: Package to load files saved by Cohaerentia Interferometric Interrogator.
Author: Marco Brunero
Author-email: marco.brunero@cohaerentia.com
Requires-Python: >=3.12,<4.0
Classifier: Programming Language :: Python :: 3
Classifier: Programming Language :: Python :: 3.12
Classifier: Programming Language :: Python :: 3.13
Requires-Dist: h5py (>=3.13.0,<4.0.0)
Requires-Dist: nptdms (>=1.10.0,<2.0.0)
Requires-Dist: scipy (>=1.15.2,<2.0.0)
